{
  "Id": "debug_item",
  "ItemName": "Debug Item",
  "Description": "This is a debug item used for testing purposes.",
  "Effects": [
    {
      "EffectIds": [
        "deal_damage"
      ],
      "Charges": -1,
      "EffectTriggers": [2],
      "Cooldown": 0.1,
      "TargetingMode": {
        "TargetingType": 1,
        "Range": 5.0,
        "AllowMultipleTargets": false
      },
      "EffectParams": [["0.5"]]
    },
    {
      "EffectIds": [
        "deal_damage"
      ],
      "Charges": -1,
      "EffectTriggers": [1],
      "Cooldown": 3.0,
      "TargetingMode": {
        "TargetingType": 3,
        "Range": 5.0,
        "TravelTime": 1.0,
        "AllowMultipleTargets": false
      },
      "EffectParams": [["0.5"]]
    }
  ],
  "EquipmentSlot": 0
}